{
  "extras": [
    "lazyvim.plugins.extras.coding.nvim-cmp",
    "lazyvim.plugins.extras.coding.yanky",
    "lazyvim.plugins.extras.editor.inc-rename",
    "lazyvim.plugins.extras.lang.json",
    "lazyvim.plugins.extras.lang.nix",
    "lazyvim.plugins.extras.lang.omnisharp",
    "lazyvim.plugins.extras.lang.sql",
    "lazyvim.plugins.extras.lang.tailwind",
    "lazyvim.plugins.extras.lang.yaml",
    "lazyvim.plugins.extras.util.dot",
    "lazyvim.plugins.extras.util.mini-hipatterns",
    "lazyvim.plugins.extras.util.project",
    "lazyvim.plugins.extras.util.rest"
  ],
  "install_version": 8,
  "news": {
    "NEWS.md": "10960"
  },
  "version": 8
}